nnxlm/__init__.py
nnxlm/glm4.py
nnxlm/granite.py
nnxlm/llama.py
nnxlm/qwen2.py
nnxlm/qwen3.py
nnxlm/utils.py
nnx_lm-0.0.1a2.dist-info/METADATA
nnx_lm-0.0.1a2.dist-info/WHEEL
nnx_lm-0.0.1a2.dist-info/entry_points.txt
nnx_lm-0.0.1a2.dist-info/top_level.txt
nnx_lm-0.0.1a2.dist-info/RECORD
