Metadata-Version: 2.2
Name: nnx-lm
Version: 0.0.1a2
Summary: nnx-lm: A portable, pip-installable CLI for running LLMs via JAX on any hardware backend.
Home-page: https://github.com/jaco-bro/nnx-lm
Author: J Joe
Author-email: backupjjoe@gmail.com
License: Apache-2.0
Requires-Dist: jax-metal==0.1.1; platform_system == "Darwin"
Requires-Dist: jaxlib==0.5.0; platform_system == "Darwin"
Requires-Dist: jax==0.5.0; platform_system == "Darwin"
Requires-Dist: flax==0.10.4
Requires-Dist: safetensors
Requires-Dist: pydantic
Requires-Dist: huggingface-hub
Requires-Dist: tokenizerz==0.0.2a5
Provides-Extra: gpu
Requires-Dist: jax[cuda12]; extra == "gpu"
Provides-Extra: tpu
Requires-Dist: jax[tpu]; extra == "tpu"
Dynamic: author
Dynamic: author-email
Dynamic: description
Dynamic: description-content-type
Dynamic: home-page
Dynamic: license
Dynamic: provides-extra
Dynamic: requires-dist
Dynamic: summary
